wagtail_code_blog/__init__.py
wagtail_code_blog/apps.py
wagtail_code_blog/migrations/0001_initial.py
wagtail_code_blog/migrations/0002_auto_20200302_0745.py
wagtail_code_blog/migrations/0003_auto_20200307_0845.py
wagtail_code_blog/migrations/0004_auto_20200317_1728.py
wagtail_code_blog/migrations/0005_blogindexpage_search_image.py
wagtail_code_blog/migrations/__init__.py
wagtail_code_blog/models.py
wagtail_code_blog/static/wagtail_code_blog/css/blog_index_page.css
wagtail_code_blog/static/wagtail_code_blog/css/markdown_code_blocks.css
wagtail_code_blog/static/wagtail_code_blog/css/pygments.css
wagtail_code_blog/static/wagtail_code_blog/css/responsive_width.css
wagtail_code_blog/static/wagtail_code_blog/images/default_user.png
wagtail_code_blog/static/wagtail_code_blog/input.css
wagtail_code_blog/templates/wagtail_code_blog/blog_index_page.html
wagtail_code_blog/templates/wagtail_code_blog/blog_index_page_body.html
wagtail_code_blog/templates/wagtail_code_blog/blog_index_page_head.html
wagtail_code_blog/templates/wagtail_code_blog/blog_page.html
wagtail_code_blog/templates/wagtail_code_blog/blog_page_body.html
wagtail_code_blog/templates/wagtail_code_blog/blog_page_head.html
wagtail_code_blog/templates/wagtail_code_blog/static_dependencies.html
wagtail_code_blog-0.5.5.dist-info/METADATA
wagtail_code_blog-0.5.5.dist-info/WHEEL
wagtail_code_blog-0.5.5.dist-info/RECORD
