Metadata-Version: 2.3
Name: wagtail-code-blog
Version: 0.5.5
Summary: A wagtail code blog
Home-page: https://github.com/honeylogic-io/wagtail-code-blog
License: MIT
Keywords: wagtail,django,blog,cms
Author: Dani Hodovic
Author-email: dani.hodovic@gmail.com
Requires-Python: >=3.9,<4.0
Classifier: Development Status :: 5 - Production/Stable
Classifier: Environment :: Web Environment
Classifier: Framework :: Django
Classifier: Framework :: Django :: 4.0
Classifier: Framework :: Django :: 5.0
Classifier: Intended Audience :: Developers
Classifier: License :: OSI Approved :: MIT License
Classifier: Operating System :: OS Independent
Classifier: Programming Language :: Python
Classifier: Programming Language :: Python :: 3
Classifier: Programming Language :: Python :: 3.9
Classifier: Programming Language :: Python :: 3.10
Classifier: Programming Language :: Python :: 3.11
Classifier: Programming Language :: Python :: 3.12
Classifier: Programming Language :: Python :: 3.13
Requires-Dist: beautifulsoup4 (==4.*)
Requires-Dist: django (>=3.dev0,<6.dev0)
Requires-Dist: django-json-ld (==0.*)
Requires-Dist: django-model-utils (>=4.dev0,<6.dev0)
Requires-Dist: readtime (>=1.dev0,<4.dev0)
Requires-Dist: wagtail (>=5.dev0,<8.dev0)
Requires-Dist: wagtail-metadata (>=4.dev0,<7.dev0)
Project-URL: Documentation, https://github.com/honeylogic-io/wagtail-code-blog
Project-URL: Repository, https://github.com/honeylogic-io/wagtail-code-blog
